arithmetic_compressor/__init__.py
arithmetic_compressor/arithmetic_coding.py
arithmetic_compressor/compress.py
arithmetic_compressor/util.py
arithmetic_compressor/models/__init__.py
arithmetic_compressor/models/base_adaptive_model.py
arithmetic_compressor/models/binary_ppm.py
arithmetic_compressor/models/context_mixing_linear.py
arithmetic_compressor/models/context_mixing_logistic.py
arithmetic_compressor/models/ppm.py
arithmetic_compressor/models/static_model.py
tests/__init__.py
tests/test_arithmetic_coder.py
tests/test_compress.py
arithmetic_compressor-0.2.dist-info/LICENSE
arithmetic_compressor-0.2.dist-info/METADATA
arithmetic_compressor-0.2.dist-info/WHEEL
arithmetic_compressor-0.2.dist-info/top_level.txt
arithmetic_compressor-0.2.dist-info/RECORD
