Metadata-Version: 2.1
Name: arithmetic_compressor
Version: 0.2
Summary: An implementation of the Arithmetic Coding algorithm in Python, along with advanced models like PPM (Prediction by Partial Matching), Context Mixing and Simple Adaptive models
Home-page: https://github.com/kodejuice/arithmetic-compressor
Author: Biereagu Sochima
Author-email: <sochima.eb@gmail.com>
License: UNKNOWN
Keywords: arithmetic,coding,ppm,encoding,encoder,prediction,context mixing,adaptive models
Platform: UNKNOWN
Classifier: Programming Language :: Python :: 3
Classifier: Intended Audience :: Developers
Classifier: License :: OSI Approved :: MIT License
Classifier: Operating System :: OS Independent
Requires-Python: >=3.7
License-File: LICENSE
